immerframe/__init__.py
tests/__init__.py
tests/test_immerframe.py
immerframe-0.0.2.dist-info/LICENSE
immerframe-0.0.2.dist-info/METADATA
immerframe-0.0.2.dist-info/WHEEL
immerframe-0.0.2.dist-info/top_level.txt
immerframe-0.0.2.dist-info/RECORD
