Metadata-Version: 2.1
Name: immerframe
Version: 0.0.2
Summary: creates the next immutable object by simply modifying the current one
Home-page: https://github.com/leontrolski/immerframe
Author: Oliver Russell
Author-email: ojhrussell@gmail.com
License: MIT License
Platform: UNKNOWN
Classifier: Development Status :: 3 - Alpha
Classifier: Intended Audience :: Developers
Classifier: License :: OSI Approved :: MIT License
Classifier: Programming Language :: Python
Classifier: Programming Language :: Python :: 3.2
Classifier: Programming Language :: Python :: 3.3
Classifier: Programming Language :: Python :: 3.4
Classifier: Programming Language :: Python :: 3.5
Classifier: Topic :: Software Development
Requires-Dist: attrs
Provides-Extra: testing
Requires-Dist: pytest ; extra == 'testing'
